<?xml version="1.0" encoding="UTF-8"?>
<fiche xmlns:xsi="http://www.w3.org/2001/XMLSchema-instance"
    xsi:noNamespaceSchemaLocation="plante_TextViz.xsd">
    <description>
        <taxon type="variete">Alyssum maritimum 'Nuit d'Orient'</taxon>    
    <parent type = "espece">Alyssum maritimum</parent>
        <contenu>
            <paragraphe>
                <titre>Alyssum maritimum 'Nuit d'Orient'</titre>
                <alinea>
                     Très compact. Hauteur 10 cm. Coloris très soutenu, violet pourpre foncé.
                </alinea>
            </paragraphe>
         </contenu>
   
    <classeVilmorin type= "fleur"/>
        </description>
</fiche>
