<?xml version="1.0" encoding="UTF-8"?>
<fiche xmlns:xsi="http://www.w3.org/2001/XMLSchema-instance" xsi:noNamespaceSchemaLocation="plante_TextViz.xsd">
  <description>
    <taxon type="espece">Géranium sanguineum</taxon>
    <parent type="genre">Geranium</parent>
    <contenu>
      <paragraphe>
        <titre>GERANIUM SANGUINEUM</titre>
        <alinea> Touffe étalée, rhizomateuse. Petites feuilles à lobes entaillés, non dentés, vert intense.</alinea>
      </paragraphe>
      <paragraphe>
        <titre>Attrait / Intérêt</titre>
        <alinea>fleurs rose magenta à rose rougeâtre de mai à septembre.</alinea>
      </paragraphe>
      <paragraphe>
        <titre>Sol / Exposition</titre>
        <alinea>exposition ensoleillée et chaude. Supporte la mi-ombre.</alinea>
      </paragraphe>
      <paragraphe>
        <titre>Culture</titre>
        <alinea>semis ou division des touffes au printemps. Jeunes plants disponibles dans le commerce en automne et au printemps.</alinea>
      </paragraphe>
      <paragraphe>
        <titre>Utilisation</titre>
        <alinea>bordure de massifs, talus.</alinea>
      </paragraphe>
      <paragraphe>
        <titre>Variétés</titre>
        <alinea>• 'Max Frei' grandes fleurs rose carminé. • 'Album' fleurs blanches.</alinea>
      </paragraphe>
    </contenu>
    <maladies />
    <photos_plante>
      <photo_plante>
        <titre_photo>Géranium sanguineum 'Album'</titre_photo>
        <fichier_photo_plante>??</fichier_photo_plante>
      </photo_plante>
    </photos_plante>
    <classeVilmorin type="fleur" />
  </description>
</fiche>

